odoo/addons/stock_storage_type/README.rst
odoo/addons/stock_storage_type/__init__.py
odoo/addons/stock_storage_type/__manifest__.py
odoo/addons/stock_storage_type/demo/product_packaging.xml
odoo/addons/stock_storage_type/demo/stock_location.xml
odoo/addons/stock_storage_type/demo/stock_package_type.xml
odoo/addons/stock_storage_type/demo/stock_storage_category.xml
odoo/addons/stock_storage_type/demo/stock_storage_category_allow_new_product_cond.xml
odoo/addons/stock_storage_type/demo/stock_storage_category_capacity.xml
odoo/addons/stock_storage_type/demo/stock_storage_location_sequence.xml
odoo/addons/stock_storage_type/i18n/de.po
odoo/addons/stock_storage_type/i18n/es.po
odoo/addons/stock_storage_type/i18n/es_AR.po
odoo/addons/stock_storage_type/i18n/fr.po
odoo/addons/stock_storage_type/i18n/it.po
odoo/addons/stock_storage_type/i18n/stock_storage_type.pot
odoo/addons/stock_storage_type/models/__init__.py
odoo/addons/stock_storage_type/models/stock_location.py
odoo/addons/stock_storage_type/models/stock_package_level.py
odoo/addons/stock_storage_type/models/stock_package_type.py
odoo/addons/stock_storage_type/models/stock_quant.py
odoo/addons/stock_storage_type/models/stock_quant_package.py
odoo/addons/stock_storage_type/models/stock_storage_category.py
odoo/addons/stock_storage_type/models/stock_storage_category_allow_new_product.py
odoo/addons/stock_storage_type/models/stock_storage_category_allow_new_product_cond.py
odoo/addons/stock_storage_type/models/stock_storage_condition_mixin.py
odoo/addons/stock_storage_type/models/stock_storage_location_sequence.py
odoo/addons/stock_storage_type/models/stock_storage_location_sequence_cond.py
odoo/addons/stock_storage_type/readme/CONTRIBUTORS.md
odoo/addons/stock_storage_type/readme/DESCRIPTION.md
odoo/addons/stock_storage_type/readme/ROADMAP.md
odoo/addons/stock_storage_type/readme/USAGE.md
odoo/addons/stock_storage_type/security/ir.model.access.csv
odoo/addons/stock_storage_type/static/description/icon.png
odoo_addon_stock_storage_type-18.0.1.5.2.dist-info/METADATA
odoo_addon_stock_storage_type-18.0.1.5.2.dist-info/WHEEL
odoo_addon_stock_storage_type-18.0.1.5.2.dist-info/top_level.txt
odoo_addon_stock_storage_type-18.0.1.5.2.dist-info/RECORD
