Metadata-Version: 2.1
Name: odoo-addon-stock_storage_type
Version: 18.0.1.5.2
Requires-Python: >=3.10
Requires-Dist: odoo-addon-stock_location_pending_move==18.0.*
Requires-Dist: odoo-addon-stock_putaway_hook==18.0.*
Requires-Dist: odoo-addon-stock_quant_package_dimension==18.0.*
Requires-Dist: odoo-addon-stock_storage_category_capacity_name==18.0.*
Requires-Dist: odoo==18.0.*
Summary: Manage packages and locations storage types
Home-page: https://github.com/OCA/stock-logistics-putaway
License: AGPL-3
Author: Camptocamp, BCIM, Odoo Community Association (OCA)
Author-email: support@odoo-community.org
Classifier: Programming Language :: Python
Classifier: Framework :: Odoo
Classifier: Framework :: Odoo :: 18.0
Classifier: License :: OSI Approved :: GNU Affero General Public License v3
Classifier: Development Status :: 4 - Beta
